devilsms/__init__.py
devilsms/__main__.py
devilsms-1.2.dist-info/LICENSE
devilsms-1.2.dist-info/METADATA
devilsms-1.2.dist-info/WHEEL
devilsms-1.2.dist-info/top_level.txt
devilsms-1.2.dist-info/RECORD
