Metadata-Version: 2.1
Name: devilsms
Version: 1.2
Summary: Python IsntaBot for spaming
Home-page: https://github.com/Sandeepdhabai/Devilbomber
Author: sm02present , SM02
Author-email: rajnikantmahato@gmail.com
Project-URL: Bug Tracker, https://github.com/Sandeepdhabai/Devilbomber/issues
Classifier: Programming Language :: Python :: 3
Classifier: Programming Language :: Python :: 3.5
Classifier: Programming Language :: Python :: 3.7
Classifier: License :: OSI Approved :: MIT License
Classifier: Operating System :: OS Independent
Requires-Python: >=3.5
License-File: LICENSE
